Workbook

Sheet Transaction Summary
A1: DELL TECHNOLOGIES / EMC CORPORATION LBO
A2: Transaction Overview
A3: Acquirer: | B3: Dell Inc.
A4: Target: | B4: EMC Corporation
A5: Announcement Date: | B5: October 12, 2015
A6: Close Date: | B6: September 7, 2016
A7: Deal Type: | B7: Leveraged Buyout
A9: Purchase Price
A10: Price per Share (Cash): | B10: 33.15
A11: Shares Outstanding (mm): | B11: 651.5
A12: Equity Value ($ mm): | B12: =B7*B8
A13: Less: Net Debt ($ mm): | B13: 4170
A14: Enterprise Value ($ mm): | B14: =B9-B10
A16: Entry Valuation
A17: FY2015 Revenue ($ mm): | B17: 24800
A18: FY2015 EBITDA ($ mm): | B18: 4700
A19: Entry EV/EBITDA Multiple: | B19: =B11/B13
A20: Entry EV/Revenue Multiple: | B20: =B11/B12
A22: SOURCES & USES OF FUNDS
A23: SOURCES | B23: $ mm | C23: %
A24: Senior Secured Debt (Term Loan): | B24: 9750
A25: Senior Unsecured Notes: | B25: 5500
A26: Mezzanine / Subordinated Debt: | B26: 1750
A27: Sponsor Equity (Dell + Partners): | B27: 11100
A28: Seller Financing: | B28: 1850
A29: Total Sources: | B29: =SUM(B24:B28) | C29: =B29/B29
A31: USES | B31: $ mm | C31: %
A32: Equity Purchase Price: | B32: 21600
A33: Less: Debt Assumed: | B33: -4170
A34: Transaction Fees & Expenses: | B34: 350
A35: Working Capital & Other: | B35: 820
A36: Total Uses: | B36: =SUM(B32:B35) | C36: =B36/B36

Sheet Historical Financials
A1: EMC CORPORATION - HISTORICAL FINANCIALS
A2: Fiscal Year Ended December 31 ($ mm)
A3: Line Item | B3: 2012 | C3: 2013 | D3: 2014 | E3: 2015 | F3: Avg Growth
A4: INCOME STATEMENT
A5: Revenue | B5: 21700 | C5: 23200 | D5: 24400 | E5: 24800 | F5: =(E4/B4)^(1/3)-1
A6: Cost of Revenue | B6: 12500 | C6: 13300 | D6: 14000 | E6: 14300 | F6: 57.7
A7: Gross Profit | B7: =B4-B6 | C7: =C4-C6 | D7: =D4-D6 | E7: =E4-E6 | F7: =AVERAGE(B7/B4,C7/C4,D7/D4,E7/E4)
A8: SG&A Expense | B8: 7500 | C8: 7800 | D8: 8100 | E8: 8200 | F8: =AVERAGE(B8/B4,C8/C4,D8/D4,E8/E4)
A9: EBITDA | B9: =B7-B8 | C9: =C7-C8 | D9: =D7-D8 | E9: =E7-E8 | F9: =AVERAGE(B9/B4,C9/C4,D9/D4,E9/E4)
A10: Depreciation & Amortization | B10: 1200 | C10: 1250 | D10: 1300 | E10: 1350 | F10: =AVERAGE(B10/B4,C10/C4,D10/D4,E10/E4)
A11: EBIT | B11: =B9-B10 | C11: =C9-C10 | D11: =D9-D10 | E11: =E9-E10 | F11: =AVERAGE(B11/B4,C11/C4,D11/D4,E11/E4)
A13: BALANCE SHEET SUMMARY
A14: Cash & Equivalents | B14: 3200 | C14: 3500 | D14: 3800 | E14: 4200
A15: Accounts Receivable | B15: 5200 | C15: 5600 | D15: 5900 | E15: 6000
A16: Total Current Assets | B16: 12000 | C16: 13000 | D16: 14100 | E16: 15000
A17: Goodwill & Intangibles | B17: 23500 | C17: 24200 | D17: 25100 | E17: 25800
A18: Total Assets | B18: 52000 | C18: 54500 | D18: 57200 | E18: 60000
A20: Accounts Payable | B20: 3500 | C20: 3700 | D20: 3900 | E20: 4100
A21: Total Current Liabilities | B21: 8500 | C21: 9200 | D21: 10000 | E21: 10500
A22: Long-term Debt | B22: 8500 | C22: 8800 | D22: 9000 | E22: 9100
A23: Total Liabilities | B23: 20000 | C23: 21500 | D23: 23500 | E23: 24800
A24: Shareholders' Equity | B24: =B26-B29 | C24: =C26-C29 | D24: =D26-D29 | E24: =E26-E29

Sheet Projections
A1: EMC CORPORATION - PROJECTED FINANCIALS
A2: Fiscal Years 2016-2021 ($ mm)
A3: KEY ASSUMPTIONS
A4: Revenue Growth Rate: | B4: 0.04
A5: EBITDA Margin (2016): | B5: 0.19
A6: EBITDA Margin (2021): | B6: 0.21
A7: D&A as % of Revenue: | B7: 0.054
A8: Tax Rate: | B8: 0.35
A9: CapEx as % of Revenue: | B9: 0.04
A11: Line Item | B11: 2016 | C11: 2017 | D11: 2018 | E11: 2019 | F11: 2020 | G11: 2021
A12: INCOME STATEMENT
A13: Revenue | B13: 25800 | C13: =B13*(1+$B$4) | D13: =C13*(1+$B$4) | E13: =D13*(1+$B$4) | F13: =E13*(1+$B$4) | G13: =F13*(1+$B$4)
A14: EBITDA | B14: =B13*$B$5 | C14: =C13*($B$5+(3-2)*($B$6-$B$5)/5) | D14: =D13*($B$5+(4-2)*($B$6-$B$5)/5) | E14: =E13*($B$5+(5-2)*($B$6-$B$5)/5) | F14: =F13*($B$5+(6-2)*($B$6-$B$5)/5) | G14: =G13*($B$5+(7-2)*($B$6-$B$5)/5)
A15: Less: D&A | B15: =B13*$B$7 | C15: =C13*$B$7 | D15: =D13*$B$7 | E15: =E13*$B$7 | F15: =F13*$B$7 | G15: =G13*$B$7
A16: EBIT | B16: =B14-B15 | C16: =C14-C15 | D16: =D14-D15 | E16: =E14-E15 | F16: =F14-F15 | G16: =G14-G15
A17: Less: Interest Expense | B17: 950 | C17: =C16*0.05 | D17: =D16*0.05 | E17: =E16*0.05 | F17: =F16*0.05 | G17: =G16*0.05
A18: EBT | B18: =B16-B17 | C18: =C16-C17 | D18: =D16-D17 | E18: =E16-E17 | F18: =F16-F17 | G18: =G16-G17
A19: Less: Taxes | B19: =B18*$B$8 | C19: =C18*$B$8 | D19: =D18*$B$8 | E19: =E18*$B$8 | F19: =F18*$B$8 | G19: =G18*$B$8
A20: Net Income | B20: =B18-B19 | C20: =C18-C19 | D20: =D18-D19 | E20: =E18-E19 | F20: =F18-F19 | G20: =G18-G19
A22: CASH FLOW ANALYSIS
A23: Net Income | B23: =B20 | C23: =C20 | D23: =D20 | E23: =E20 | F23: =F20 | G23: =G20
A24: Plus: D&A | B24: =B15 | C24: =C15 | D24: =D15 | E24: =E15 | F24: =F15 | G24: =G15
A25: Less: CapEx | B25: =B13*$B$9 | C25: =C13*$B$9 | D25: =D13*$B$9 | E25: =E13*$B$9 | F25: =F13*$B$9 | G25: =G13*$B$9
A26: Less: Change in NWC | B26: 50 | C26: 50 | D26: 50 | E26: 50 | F26: 50 | G26: 50
A27: Free Cash Flow | B27: =B23+B24-B25-B26 | C27: =C23+C24-C25-C26 | D27: =D23+D24-D25-D26 | E27: =E23+E24-E25-E26 | F27: =F23+F24-F25-F26 | G27: =G23+G24-G25-G26

Sheet Debt Schedule
A1: DEBT SCHEDULE & LEVERAGE ANALYSIS
A2: Fiscal Years 2016-2021 ($ mm)
A3: DEBT ASSUMPTIONS
A4: Senior Secured Term Loan: | B4: 9750
A5: Senior Unsecured Notes: | B5: 5500
A6: Mezzanine Debt: | B6: 1750
A7: Total Debt at Close: | B7: =B4+B5+B6
A8: Term Loan Interest Rate: | B8: 0.042
A9: Senior Notes Interest Rate: | B9: 0.055
A10: Mezzanine Interest Rate: | B10: 0.075
A11: Term Loan Amortization %: | B11: 0.01
A13: Line Item | B13: 2016 | C13: 2017 | D13: 2018 | E13: 2019 | F13: 2020 | G13: 2021
A14: TERM LOAN BALANCE
A15: Beginning Balance | B15: 9750 | C15: =B17 | D15: =C17 | E15: =D17 | F15: =E17 | G15: =F17
A16: Less: Amortization | B16: =B15*$B$11 | C16: =C15*$B$11 | D16: =D15*$B$11 | E16: =E15*$B$11 | F16: =F15*$B$11 | G16: =G15*$B$11
A17: Ending Balance | B17: =B15-B16 | C17: =C15-C16 | D17: =D15-D16 | E17: =E15-E16 | F17: =F15-F16 | G17: =G15-G16
A19: INTEREST EXPENSE
A20: Term Loan Interest | B20: =B15*$B$8 | C20: =C15*$B$8 | D20: =D15*$B$8 | E20: =E15*$B$8 | F20: =F15*$B$8 | G20: =G15*$B$8
A21: Senior Notes Interest | B21: =5500*$B$9 | C21: =5500*$B$9 | D21: =5500*$B$9 | E21: =5500*$B$9 | F21: =5500*$B$9 | G21: =5500*$B$9
A22: Mezzanine Interest | B22: =1750*$B$10 | C22: =1750*$B$10 | D22: =1750*$B$10 | E22: =1750*$B$10 | F22: =1750*$B$10 | G22: =1750*$B$10
A23: Total Interest Expense | B23: =B20+B21+B22 | C23: =C20+C21+C22 | D23: =D20+D21+D22 | E23: =E20+E21+E22 | F23: =F20+F21+F22 | G23: =G20+G21+G22
A25: LEVERAGE ANALYSIS
A26: Total Debt | B26: =B17+5500+1750 | C26: =C17+5500+1750 | D26: =D17+5500+1750 | E26: =E17+5500+1750 | F26: =F17+5500+1750 | G26: =G17+5500+1750
A27: Less: Cash | B27: 4200 | C27: 4200 | D27: 4200 | E27: 4200 | F27: 4200 | G27: 4200
A28: Net Debt | B28: =B26-B27 | C28: =C26-C27 | D28: =D26-D27 | E28: =E26-E27 | F28: =F26-F27 | G28: =G26-G27
A29: EBITDA (from Projections) | B29: =Projections!B8 | C29: =Projections!C8 | D29: =Projections!D8 | E29: =Projections!E8 | F29: =Projections!F8 | G29: =Projections!G8
A30: Net Debt / EBITDA Leverage | B30: =B28/B29 | C30: =C28/C29 | D30: =D28/D29 | E30: =E28/E29 | F30: =F28/F29 | G30: =G28/G29

Sheet Returns Analysis
A1: LBO RETURNS ANALYSIS
A2: Exit Scenarios - Multiple Exit Assumptions
A4: Entry Enterprise Value ($ mm): | B4: 24950
A5: Entry EBITDA (FY2015): | B5: 4700
A6: Entry EV/EBITDA Multiple: | B6: =B4/B5
A7: Initial Equity Investment: | B7: 11100
A9: Exit Year EBITDA (FY2021): | B9: =Projections!G8
A10: Exit Net Debt (FY2021): | B10: =Projections!G37-4200
A12: IRR SENSITIVITY - Exit Multiple
A13: Exit Multiple (EBITDA): | B13: 7.0x | C13: 8.0x | D13: 9.0x | E13: 10.0x | F13: 11.0x
A14: Year 5 Exit | B14: =(((B$9*7.0)-B$10)/B$7)^(1/5)-1 | C14: =(((B$9*8.0)-B$10)/B$7)^(1/5)-1 | D14: =(((B$9*9.0)-B$10)/B$7)^(1/5)-1 | E14: =(((B$9*10.0)-B$10)/B$7)^(1/5)-1 | F14: =(((B$9*11.0)-B$10)/B$7)^(1/5)-1
A15: Year 6 Exit | B15: =(((B$9*7.0)-B$10)/B$7)^(1/6)-1 | C15: =(((B$9*8.0)-B$10)/B$7)^(1/6)-1 | D15: =(((B$9*9.0)-B$10)/B$7)^(1/6)-1 | E15: =(((B$9*10.0)-B$10)/B$7)^(1/6)-1 | F15: =(((B$9*11.0)-B$10)/B$7)^(1/6)-1
A18: EQUITY VALUE AT EXIT
A19: Exit Multiple: | B19: 7.0x | C19: 9.0x | D19: 11.0x
A20: Exit EV: | B20: =B$9*7.0 | C20: =B$9*9.0 | D20: =B$9*11.0
A21: Less: Exit Net Debt: | B21: =B$10 | C21: =B$10 | D21: =B$10
A22: Equity Value: | B22: =B20-B21 | C22: =C20-C21 | D22: =D20-D21
A23: Initial Equity: | B23: =B$7 | C23: =B$7 | D23: =B$7
A24: MOIC (Money Multiple): | B24: =B22/B23 | C24: =C22/C23 | D24: =D22/D23
A25: 5-Year IRR: | B25: =((B22/B$7)^(1/5))-1 | C25: =((C22/B$7)^(1/5))-1 | D25: =((D22/B$7)^(1/5))-1

Sheet Sensitivity Analysis
A1: LBO SENSITIVITY ANALYSIS
A3: 2D SENSITIVITY: 5-Year IRR by Exit Multiple & Year
A4: Exit Multiple / Year | B4: 7.0x | C4: 8.0x | D4: 9.0x | E4: 10.0x | F4: 11.0x
A5: Year 4 | B5: =(((4738*7.0)-12750)/(11100))^(1/4)-1 | C5: =(((4738*8.0)-12750)/(11100))^(1/4)-1 | D5: =(((4738*9.0)-12750)/(11100))^(1/4)-1 | E5: =(((4738*10.0)-12750)/(11100))^(1/4)-1 | F5: =(((4738*11.0)-12750)/(11100))^(1/4)-1
A6: Year 5 | B6: =(((4738*7.0)-12750)/(11100))^(1/5)-1 | C6: =(((4738*8.0)-12750)/(11100))^(1/5)-1 | D6: =(((4738*9.0)-12750)/(11100))^(1/5)-1 | E6: =(((4738*10.0)-12750)/(11100))^(1/5)-1 | F6: =(((4738*11.0)-12750)/(11100))^(1/5)-1
A7: Year 6 | B7: =(((4738*7.0)-12750)/(11100))^(1/6)-1 | C7: =(((4738*8.0)-12750)/(11100))^(1/6)-1 | D7: =(((4738*9.0)-12750)/(11100))^(1/6)-1 | E7: =(((4738*10.0)-12750)/(11100))^(1/6)-1 | F7: =(((4738*11.0)-12750)/(11100))^(1/6)-1
A8: Year 7 | B8: =(((4738*7.0)-12750)/(11100))^(1/7)-1 | C8: =(((4738*8.0)-12750)/(11100))^(1/7)-1 | D8: =(((4738*9.0)-12750)/(11100))^(1/7)-1 | E8: =(((4738*10.0)-12750)/(11100))^(1/7)-1 | F8: =(((4738*11.0)-12750)/(11100))^(1/7)-1
A11: 2D SENSITIVITY: Exit Enterprise Value ($mm)
A12: Revenue Growth / EBITDA % | B12: 19.0% | C12: 19.5% | D12: 20.0% | E12: 20.5% | F12: 21.0%
A13: 3.0% | B13: 51893.745 | C13: 53259.37 | D13: 54624.994 | E13: 55990.619 | F13: 57356.244
A14: 3.5% | B14: 53165.59 | C14: 54564.684 | D14: 55963.779 | E14: 57362.873 | F14: 58761.968
A15: 4.0% | B15: 54462.251 | C15: 55895.468 | D15: 57328.685 | E15: 58761.902 | F15: 60195.119
A16: 4.5% | B16: 55784.088 | C16: 57252.091 | D16: 58720.093 | E16: 60188.095 | F16: 61656.098
A17: 5.0% | B17: 57131.468 | C17: 58634.928 | D17: 60138.387 | E17: 61641.847 | F17: 63145.307
